{"env_name": "huzzah", "libsource_dirs": ["c:\\Users\\kbdeir\\Documents\\PlatformIO\\Projects\\SmartConfig\\lib", "c:\\Users\\kbdeir\\Documents\\PlatformIO\\Projects\\SmartConfig\\.pio\\libdeps\\huzzah", "C:\\Users\\kbdeir\\.platformio\\lib", "C:\\Users\\kbdeir\\.platformio\\packages\\framework-arduinoespressif8266\\libraries"], "defines": ["PLATFORMIO=60104", "ESP8266", "ARDUINO_ARCH_ESP8266", "ARDUINO_ESP8266_ADAFRUIT_HUZZAH", "DEBUG_FAUXMO=Serial", "DEBUG_FAUXMO_VERBOSE_TCP=0", "DEBUG_FAUXMO_VERBOSE_UDP=0", "PIO_FRAMEWORK_ARDUINO_LWIP_HIGHER_BANDWIDTH", "F_CPU=80000000L", "__ets__", "ICACHE_FLASH", "ARDUINO=10805", "ARDUINO_BOARD=\"PLATFORMIO_HUZZAH\"", "FLASHMODE_QIO", "LWIP_OPEN_SRC", "NONOSDK22x_190703=1", "TCP_MSS=536", "LWIP_FEATURES=1", "LWIP_IPV6=0", "VTABLES_IN_FLASH", "MMU_IRAM_SIZE=0x8000", "MMU_ICACHE_SIZE=0x8000"], "includes": {"build": ["c:\\Users\\kbdeir\\Documents\\PlatformIO\\Projects\\SmartConfig\\include", "c:\\Users\\kbdeir\\Documents\\PlatformIO\\Projects\\SmartConfig\\src", "c:\\Users\\kbdeir\\Documents\\PlatformIO\\Projects\\SmartConfig\\include", "c:\\Users\\kbdeir\\Documents\\PlatformIO\\Projects\\SmartConfig\\src", "C:\\Users\\kbdeir\\.platformio\\packages\\framework-arduinoespressif8266\\libraries\\Wire", "C:\\Users\\kbdeir\\.platformio\\packages\\framework-arduinoespressif8266\\libraries\\SPI", "c:\\Users\\kbdeir\\Documents\\PlatformIO\\Projects\\SmartConfig\\lib\\DallasTemperature_ID54", "C:\\Users\\kbdeir\\.platformio\\packages\\framework-arduinoespressif8266\\libraries\\SoftwareSerial\\src", "c:\\Users\\kbdeir\\Documents\\PlatformIO\\Projects\\SmartConfig\\.pio\\libdeps\\huzzah\\AsyncMqttClient_ID346\\src", "c:\\Users\\kbdeir\\Documents\\PlatformIO\\Projects\\SmartConfig\\lib\\SimpleTimer", "C:\\Users\\kbdeir\\.platformio\\packages\\framework-arduinoespressif8266\\libraries\\DNSServer\\src", "c:\\Users\\kbdeir\\Documents\\PlatformIO\\Projects\\SmartConfig\\lib\\Chronos_ID920\\src", "c:\\Users\\kbdeir\\Documents\\PlatformIO\\Projects\\SmartConfig\\lib\\Bounce2_ID1106\\src", "c:\\Users\\kbdeir\\Documents\\PlatformIO\\Projects\\SmartConfig\\lib\\OneButton_ID1260\\src", "c:\\Users\\kbdeir\\Documents\\PlatformIO\\Projects\\SmartConfig\\lib\\EmonLib-esp32", "c:\\Users\\kbdeir\\Documents\\PlatformIO\\Projects\\SmartConfig\\.pio\\libdeps\\huzzah\\AsyncPing_esp8266_\\src", "C:\\Users\\kbdeir\\.platformio\\lib\\Time", "C:\\Users\\kbdeir\\.platformio\\packages\\framework-arduinoespressif8266\\libraries\\EEPROM", "c:\\Users\\kbdeir\\Documents\\PlatformIO\\Projects\\SmartConfig\\.pio\\libdeps\\huzzah\\ESPAsyncUDP\\src", "c:\\Users\\kbdeir\\Documents\\PlatformIO\\Projects\\SmartConfig\\.pio\\libdeps\\huzzah\\HomeKit-ESP8266\\src", "C:\\Users\\kbdeir\\.platformio\\packages\\framework-arduinoespressif8266\\libraries\\ESP8266mDNS\\src", "C:\\Users\\kbdeir\\.platformio\\lib\\AccelStepper\\src", "c:\\Users\\kbdeir\\Documents\\PlatformIO\\Projects\\SmartConfig\\.pio\\libdeps\\huzzah\\FauxmoESP\\src", "c:\\Users\\kbdeir\\Documents\\PlatformIO\\Projects\\SmartConfig\\.pio\\libdeps\\huzzah\\painlessMesh\\src", "C:\\Users\\kbdeir\\.platformio\\packages\\framework-arduinoespressif8266\\libraries\\LittleFS\\src", "c:\\Users\\kbdeir\\Documents\\PlatformIO\\Projects\\SmartConfig\\.pio\\libdeps\\huzzah\\TaskScheduler\\src", "c:\\Users\\kbdeir\\Documents\\PlatformIO\\Projects\\SmartConfig\\.pio\\libdeps\\huzzah\\ArduinoJson\\src", "c:\\Users\\kbdeir\\Documents\\PlatformIO\\Projects\\SmartConfig\\.pio\\libdeps\\huzzah\\ESP Async WebServer\\src", "C:\\Users\\kbdeir\\.platformio\\packages\\framework-arduinoespressif8266\\libraries\\ESP8266WiFi\\src", "C:\\Users\\kbdeir\\.platformio\\packages\\framework-arduinoespressif8266\\libraries\\Hash\\src", "c:\\Users\\kbdeir\\Documents\\PlatformIO\\Projects\\SmartConfig\\.pio\\libdeps\\huzzah\\OneWire", "c:\\Users\\kbdeir\\Documents\\PlatformIO\\Projects\\SmartConfig\\lib\\ESPAsyncTCP_ID305\\src", "C:\\Users\\kbdeir\\.platformio\\packages\\framework-arduinoespressif8266\\tools\\sdk\\include", "C:\\Users\\kbdeir\\.platformio\\packages\\framework-arduinoespressif8266\\cores\\esp8266", "C:\\Users\\kbdeir\\.platformio\\packages\\toolchain-xtensa\\include", "C:\\Users\\kbdeir\\.platformio\\packages\\framework-arduinoespressif8266\\tools\\sdk\\lwip2\\include", "C:\\Users\\kbdeir\\.platformio\\packages\\framework-arduinoespressif8266\\variants\\adafruit"], "compatlib": ["c:\\Users\\kbdeir\\Documents\\PlatformIO\\Projects\\SmartConfig\\lib\\Bounce2_ID1106\\src", "c:\\Users\\kbdeir\\Documents\\PlatformIO\\Projects\\SmartConfig\\lib\\Bounce2_ID1106\\src", "c:\\Users\\kbdeir\\Documents\\PlatformIO\\Projects\\SmartConfig\\lib\\Chronos_ID920\\src", "c:\\Users\\kbdeir\\Documents\\PlatformIO\\Projects\\SmartConfig\\lib\\DallasTemperature_ID54", "c:\\Users\\kbdeir\\Documents\\PlatformIO\\Projects\\SmartConfig\\lib\\DallasTemperature_ID54", "c:\\Users\\kbdeir\\Documents\\PlatformIO\\Projects\\SmartConfig\\.pio\\libdeps\\huzzah\\OneWire", "c:\\Users\\kbdeir\\Documents\\PlatformIO\\Projects\\SmartConfig\\lib\\ESPAsyncTCP_ID305\\src", "c:\\Users\\kbdeir\\Documents\\PlatformIO\\Projects\\SmartConfig\\lib\\ESPAsyncTCP_ID305\\src", "c:\\Users\\kbdeir\\Documents\\PlatformIO\\Projects\\SmartConfig\\lib\\EmonLib-esp32", "c:\\Users\\kbdeir\\Documents\\PlatformIO\\Projects\\SmartConfig\\lib\\OneButton_ID1260\\src", "c:\\Users\\kbdeir\\Documents\\PlatformIO\\Projects\\SmartConfig\\lib\\OneButton_ID1260\\src", "c:\\Users\\kbdeir\\Documents\\PlatformIO\\Projects\\SmartConfig\\lib\\SimpleTimer", "c:\\Users\\kbdeir\\Documents\\PlatformIO\\Projects\\SmartConfig\\.pio\\libdeps\\huzzah\\ArduinoJson\\src", "c:\\Users\\kbdeir\\Documents\\PlatformIO\\Projects\\SmartConfig\\.pio\\libdeps\\huzzah\\ArduinoJson\\src", "c:\\Users\\kbdeir\\Documents\\PlatformIO\\Projects\\SmartConfig\\.pio\\libdeps\\huzzah\\AsyncMqttClient_ID346\\src", "c:\\Users\\kbdeir\\Documents\\PlatformIO\\Projects\\SmartConfig\\.pio\\libdeps\\huzzah\\AsyncMqttClient_ID346\\src", "c:\\Users\\kbdeir\\Documents\\PlatformIO\\Projects\\SmartConfig\\lib\\ESPAsyncTCP_ID305\\src", "c:\\Users\\kbdeir\\Documents\\PlatformIO\\Projects\\SmartConfig\\.pio\\libdeps\\huzzah\\AsyncPing_esp8266_\\src", "c:\\Users\\kbdeir\\Documents\\PlatformIO\\Projects\\SmartConfig\\.pio\\libdeps\\huzzah\\ESP Async WebServer\\src", "c:\\Users\\kbdeir\\Documents\\PlatformIO\\Projects\\SmartConfig\\.pio\\libdeps\\huzzah\\ESP Async WebServer\\src", "C:\\Users\\kbdeir\\.platformio\\packages\\framework-arduinoespressif8266\\libraries\\ESP8266WiFi\\src", "C:\\Users\\kbdeir\\.platformio\\packages\\framework-arduinoespressif8266\\libraries\\Hash\\src", "c:\\Users\\kbdeir\\Documents\\PlatformIO\\Projects\\SmartConfig\\lib\\ESPAsyncTCP_ID305\\src", "c:\\Users\\kbdeir\\Documents\\PlatformIO\\Projects\\SmartConfig\\.pio\\libdeps\\huzzah\\ESPAsyncUDP\\src", "c:\\Users\\kbdeir\\Documents\\PlatformIO\\Projects\\SmartConfig\\.pio\\libdeps\\huzzah\\ESPAsyncUDP\\src", "c:\\Users\\kbdeir\\Documents\\PlatformIO\\Projects\\SmartConfig\\.pio\\libdeps\\huzzah\\FauxmoESP\\src", "c:\\Users\\kbdeir\\Documents\\PlatformIO\\Projects\\SmartConfig\\.pio\\libdeps\\huzzah\\FauxmoESP\\src", "C:\\Users\\kbdeir\\.platformio\\packages\\framework-arduinoespressif8266\\libraries\\ESP8266WiFi\\src", "c:\\Users\\kbdeir\\Documents\\PlatformIO\\Projects\\SmartConfig\\lib\\ESPAsyncTCP_ID305\\src", "c:\\Users\\kbdeir\\Documents\\PlatformIO\\Projects\\SmartConfig\\.pio\\libdeps\\huzzah\\HomeKit-ESP8266\\src", "c:\\Users\\kbdeir\\Documents\\PlatformIO\\Projects\\SmartConfig\\.pio\\libdeps\\huzzah\\HomeKit-ESP8266\\src", "C:\\Users\\kbdeir\\.platformio\\packages\\framework-arduinoespressif8266\\libraries\\ESP8266mDNS\\src", "C:\\Users\\kbdeir\\.platformio\\packages\\framework-arduinoespressif8266\\libraries\\ESP8266WiFi\\src", "c:\\Users\\kbdeir\\Documents\\PlatformIO\\Projects\\SmartConfig\\.pio\\libdeps\\huzzah\\OneWire", "c:\\Users\\kbdeir\\Documents\\PlatformIO\\Projects\\SmartConfig\\.pio\\libdeps\\huzzah\\OneWire", "c:\\Users\\kbdeir\\Documents\\PlatformIO\\Projects\\SmartConfig\\.pio\\libdeps\\huzzah\\TaskScheduler\\src", "c:\\Users\\kbdeir\\Documents\\PlatformIO\\Projects\\SmartConfig\\.pio\\libdeps\\huzzah\\TaskScheduler\\src", "c:\\Users\\kbdeir\\Documents\\PlatformIO\\Projects\\SmartConfig\\.pio\\libdeps\\huzzah\\painlessMesh\\src", "c:\\Users\\kbdeir\\Documents\\PlatformIO\\Projects\\SmartConfig\\.pio\\libdeps\\huzzah\\painlessMesh\\src", "C:\\Users\\kbdeir\\.platformio\\packages\\framework-arduinoespressif8266\\libraries\\LittleFS\\src", "C:\\Users\\kbdeir\\.platformio\\packages\\framework-arduinoespressif8266\\libraries\\ESP8266WiFi\\src", "c:\\Users\\kbdeir\\Documents\\PlatformIO\\Projects\\SmartConfig\\lib\\ESPAsyncTCP_ID305\\src", "c:\\Users\\kbdeir\\Documents\\PlatformIO\\Projects\\SmartConfig\\.pio\\libdeps\\huzzah\\TaskScheduler\\src", "c:\\Users\\kbdeir\\Documents\\PlatformIO\\Projects\\SmartConfig\\.pio\\libdeps\\huzzah\\ArduinoJson\\src", "C:\\Users\\kbdeir\\.platformio\\lib\\AccelStepper\\src", "C:\\Users\\kbdeir\\.platformio\\lib\\Time", "C:\\Users\\kbdeir\\.platformio\\lib\\Time", "C:\\Users\\kbdeir\\.platformio\\packages\\framework-arduinoespressif8266\\libraries\\DNSServer\\src", "C:\\Users\\kbdeir\\.platformio\\packages\\framework-arduinoespressif8266\\libraries\\EEPROM", "C:\\Users\\kbdeir\\.platformio\\packages\\framework-arduinoespressif8266\\libraries\\ESP8266WiFi\\src", "C:\\Users\\kbdeir\\.platformio\\packages\\framework-arduinoespressif8266\\libraries\\ESP8266mDNS\\src", "C:\\Users\\kbdeir\\.platformio\\packages\\framework-arduinoespressif8266\\libraries\\Hash\\src", "C:\\Users\\kbdeir\\.platformio\\packages\\framework-arduinoespressif8266\\libraries\\LittleFS\\src", "C:\\Users\\kbdeir\\.platformio\\packages\\framework-arduinoespressif8266\\libraries\\SPI", "C:\\Users\\kbdeir\\.platformio\\packages\\framework-arduinoespressif8266\\libraries\\SoftwareSerial\\src", "C:\\Users\\kbdeir\\.platformio\\packages\\framework-arduinoespressif8266\\libraries\\SoftwareSerial\\src", "C:\\Users\\kbdeir\\.platformio\\packages\\framework-arduinoespressif8266\\libraries\\Wire", "c:\\Users\\kbdeir\\Documents\\PlatformIO\\Projects\\SmartConfig\\lib\\AH_EasyDriver", "c:\\Users\\kbdeir\\Documents\\PlatformIO\\Projects\\SmartConfig\\lib\\Bifrost library for HC-SR04_ID2019\\src", "c:\\Users\\kbdeir\\Documents\\PlatformIO\\Projects\\SmartConfig\\lib\\Debouncer_ID1267", "c:\\Users\\kbdeir\\Documents\\PlatformIO\\Projects\\SmartConfig\\lib\\New folder", "c:\\Users\\kbdeir\\Documents\\PlatformIO\\Projects\\SmartConfig\\lib\\OneWire_ID1", "c:\\Users\\kbdeir\\Documents\\PlatformIO\\Projects\\SmartConfig\\lib\\huzzah", "c:\\Users\\kbdeir\\Documents\\PlatformIO\\Projects\\SmartConfig\\.pio\\libdeps\\huzzah\\ArduinoJson@6.18.1\\src", "c:\\Users\\kbdeir\\Documents\\PlatformIO\\Projects\\SmartConfig\\.pio\\libdeps\\huzzah\\DallasTemperature", "c:\\Users\\kbdeir\\Documents\\PlatformIO\\Projects\\SmartConfig\\.pio\\libdeps\\huzzah\\ESP8266-ping\\src", "c:\\Users\\kbdeir\\Documents\\PlatformIO\\Projects\\SmartConfig\\.pio\\libdeps\\huzzah\\ESPAsyncTCP\\src", "c:\\Users\\kbdeir\\Documents\\PlatformIO\\Projects\\SmartConfig\\.pio\\libdeps\\huzzah\\OneWire_ID1", "C:\\Users\\kbdeir\\.platformio\\lib\\ACS712 Current Sensor_ID1601\\src", "C:\\Users\\kbdeir\\.platformio\\lib\\AceButton\\src", "C:\\Users\\kbdeir\\.platformio\\lib\\Adafruit Unified Sensor", "C:\\Users\\kbdeir\\.platformio\\lib\\Bounce2\\src", "C:\\Users\\kbdeir\\.platformio\\lib\\Chronos_ID920\\src", "C:\\Users\\kbdeir\\.platformio\\lib\\DHT sensor library", "C:\\Users\\kbdeir\\.platformio\\lib\\DHT sensor library for ESPx", "C:\\Users\\kbdeir\\.platformio\\lib\\ESP32WebServer_ID2007\\src", "C:\\Users\\kbdeir\\.platformio\\lib\\ESPAsyncTCP_ID305\\src", "C:\\Users\\kbdeir\\.platformio\\lib\\NTP", "C:\\Users\\kbdeir\\.platformio\\lib\\OneButton\\src", "C:\\Users\\kbdeir\\.platformio\\lib\\TaskScheduler\\src", "C:\\Users\\kbdeir\\.platformio\\lib\\Ticker", "C:\\Users\\kbdeir\\.platformio\\packages\\framework-arduinoespressif8266\\libraries\\ArduinoOTA", "C:\\Users\\kbdeir\\.platformio\\packages\\framework-arduinoespressif8266\\libraries\\ESP8266AVRISP\\src", "C:\\Users\\kbdeir\\.platformio\\packages\\framework-arduinoespressif8266\\libraries\\ESP8266HTTPClient\\src", "C:\\Users\\kbdeir\\.platformio\\packages\\framework-arduinoespressif8266\\libraries\\ESP8266HTTPUpdateServer\\src", "C:\\Users\\kbdeir\\.platformio\\packages\\framework-arduinoespressif8266\\libraries\\ESP8266LLMNR", "C:\\Users\\kbdeir\\.platformio\\packages\\framework-arduinoespressif8266\\libraries\\ESP8266NetBIOS", "C:\\Users\\kbdeir\\.platformio\\packages\\framework-arduinoespressif8266\\libraries\\ESP8266SSDP", "C:\\Users\\kbdeir\\.platformio\\packages\\framework-arduinoespressif8266\\libraries\\ESP8266SdFat\\src", "C:\\Users\\kbdeir\\.platformio\\packages\\framework-arduinoespressif8266\\libraries\\ESP8266WebServer\\src", "C:\\Users\\kbdeir\\.platformio\\packages\\framework-arduinoespressif8266\\libraries\\ESP8266WiFiMesh\\src", "C:\\Users\\kbdeir\\.platformio\\packages\\framework-arduinoespressif8266\\libraries\\ESP8266httpUpdate\\src", "C:\\Users\\kbdeir\\.platformio\\packages\\framework-arduinoespressif8266\\libraries\\Ethernet\\src", "C:\\Users\\kbdeir\\.platformio\\packages\\framework-arduinoespressif8266\\libraries\\GDBStub\\src", "C:\\Users\\kbdeir\\.platformio\\packages\\framework-arduinoespressif8266\\libraries\\I2S\\src", "C:\\Users\\kbdeir\\.platformio\\packages\\framework-arduinoespressif8266\\libraries\\Netdump\\src", "C:\\Users\\kbdeir\\.platformio\\packages\\framework-arduinoespressif8266\\libraries\\SD\\src", "C:\\Users\\kbdeir\\.platformio\\packages\\framework-arduinoespressif8266\\libraries\\SDFS\\src", "C:\\Users\\kbdeir\\.platformio\\packages\\framework-arduinoespressif8266\\libraries\\SPISlave\\src", "C:\\Users\\kbdeir\\.platformio\\packages\\framework-arduinoespressif8266\\libraries\\Servo\\src", "C:\\Users\\kbdeir\\.platformio\\packages\\framework-arduinoespressif8266\\libraries\\TFT_Touch_Shield_V2", "C:\\Users\\kbdeir\\.platformio\\packages\\framework-arduinoespressif8266\\libraries\\Ticker\\src", "C:\\Users\\kbdeir\\.platformio\\packages\\framework-arduinoespressif8266\\libraries\\esp8266\\src", "C:\\Users\\kbdeir\\.platformio\\packages\\framework-arduinoespressif8266\\libraries\\lwIP_PPP\\src", "C:\\Users\\kbdeir\\.platformio\\packages\\framework-arduinoespressif8266\\libraries\\lwIP_enc28j60\\src", "C:\\Users\\kbdeir\\.platformio\\packages\\framework-arduinoespressif8266\\libraries\\lwIP_w5100\\src", "C:\\Users\\kbdeir\\.platformio\\packages\\framework-arduinoespressif8266\\libraries\\lwIP_w5500\\src"], "toolchain": ["C:\\Users\\kbdeir\\.platformio\\packages\\toolchain-xtensa\\xtensa-lx106-elf\\include\\c++\\10.3.0", "C:\\Users\\kbdeir\\.platformio\\packages\\toolchain-xtensa\\xtensa-lx106-elf\\include\\c++\\10.3.0\\xtensa-lx106-elf", "C:\\Users\\kbdeir\\.platformio\\packages\\toolchain-xtensa\\lib\\gcc\\xtensa-lx106-elf\\10.3.0\\include", "C:\\Users\\kbdeir\\.platformio\\packages\\toolchain-xtensa\\lib\\gcc\\xtensa-lx106-elf\\10.3.0\\include-fixed", "C:\\Users\\kbdeir\\.platformio\\packages\\toolchain-xtensa\\xtensa-lx106-elf\\include"]}, "cc_flags": "-std=gnu17 -Wpointer-arith -Wno-implicit-function-declaration -Wl,-EL -fno-inline-functions -nostdlib -g -Os -mlongcalls -mtext-section-literals -falign-functions=4 -U__STRICT_ANSI__ -D_GNU_SOURCE -ffunction-sections -fdata-sections -Wall -Werror=return-type -free -fipa-pta", "cxx_flags": "-fno-rtti -std=gnu++17 -fno-exceptions -g -Os -mlongcalls -mtext-section-literals -falign-functions=4 -U__STRICT_ANSI__ -D_GNU_SOURCE -ffunction-sections -fdata-sections -Wall -Werror=return-type -free -fipa-pta", "cc_path": "C:\\Users\\kbdeir\\.platformio\\packages\\toolchain-xtensa\\bin\\xtensa-lx106-elf-gcc.exe", "cxx_path": "C:\\Users\\kbdeir\\.platformio\\packages\\toolchain-xtensa\\bin\\xtensa-lx106-elf-g++.exe", "gdb_path": "C:\\Users\\kbdeir\\.platformio\\packages\\toolchain-xtensa\\bin\\xtensa-lx106-elf-gdb.exe", "prog_path": "c:\\Users\\kbdeir\\Documents\\PlatformIO\\Projects\\SmartConfig\\.pio\\build\\huzzah\\firmware.elf", "svd_path": null, "compiler_type": "gcc", "targets": [{"name": "buildfs", "title": "Build Filesystem Image", "description": null, "group": "Platform"}, {"name": "size", "title": "Program Size", "description": "Calculate program size", "group": "Platform"}, {"name": "upload", "title": "Upload", "description": null, "group": "Platform"}, {"name": "uploadfs", "title": "Upload Filesystem Image", "description": null, "group": "Platform"}, {"name": "uploadfsota", "title": "Upload Filesystem Image OTA", "description": null, "group": "Platform"}, {"name": "erase", "title": "Erase Flash", "description": null, "group": "Platform"}], "extra": {"flash_images": []}}